GWO/__init__.py
gwo-0.1.4.dist-info/LICENSE
gwo-0.1.4.dist-info/METADATA
gwo-0.1.4.dist-info/WHEEL
gwo-0.1.4.dist-info/top_level.txt
gwo-0.1.4.dist-info/RECORD
