Metadata-Version: 2.1
Name: gwo
Version: 0.1.4
Summary: a damn fine wrapper for reverse-enginered gwo api
Home-page: https://github.com/Reb0rnEnder/GWOApi
Author: RebornEnder
Author-email: contact@dotbend.xyz
License: LICENCE
License-File: LICENSE
Requires-Dist: aiohttp[speedups]>=3.12.15
Requires-Dist: beautifulsoup4>=4.14.2
Requires-Dist: unicodeit>=0.7.5
